raster/__init__.py
raster/admin.py
raster/const.py
raster/exceptions.py
raster/mixins.py
raster/models.py
raster/rasterize.py
raster/shortcuts.py
raster/tasks.py
raster/urls.py
raster/utils.py
raster/valuecount.py
raster/views.py
raster/algebra/__init__.py
raster/algebra/const.py
raster/algebra/parser.py
raster/migrations/0001_initial.py
raster/migrations/0002_auto_20140925_0723.py
raster/migrations/0003_rastertile_level.py
raster/migrations/0004_rasterlayermetadata.py
raster/migrations/0005_auto_20141014_0955.py
raster/migrations/0006_auto_20141016_0522.py
raster/migrations/0007_auto_20141017_0240.py
raster/migrations/0008_auto_20150219_0413.py
raster/migrations/0009_rasterlayer_max_zoom.py
raster/migrations/0010_auto_20150429_1207.py
raster/migrations/0011_auto_20150615_0800.py
raster/migrations/0012_auto_20150616_0538.py
raster/migrations/0013_remove_rasterlayer_max_zoom.py
raster/migrations/0014_remove_rastertile_is_base.py
raster/migrations/0015_auto_20150819_0320.py
raster/migrations/0016_rasterlayermetadata_srid.py
raster/migrations/0017_copy_srids_20150922_0207.py
raster/migrations/0018_rasterlayermetadata_srs_wkt.py
raster/migrations/0019_remove_rasterlayer_srid.py
raster/migrations/0020_auto_20150928_0408.py
raster/migrations/0021_rasterlayerparsestatus.py
raster/migrations/0022_auto_20151110_0810.py
raster/migrations/0023_remove_rasterlayer_parse_log.py
raster/migrations/0024_auto_20151111_0532.py
raster/migrations/0025_auto_20151113_0259.py
raster/migrations/0026_auto_20151120_1334.py
raster/migrations/0027_rasterlayerreprojected.py
raster/migrations/0028_auto_20160104_0533.py
raster/migrations/0029_auto_20160111_0646.py
raster/migrations/0030_auto_20160111_0813.py
raster/migrations/0031_auto_20160218_0832.py
raster/migrations/0032_auto_20160426_0152.py
raster/migrations/0033_auto_20160510_1041.py
raster/migrations/0034_legendentryorder.py
raster/migrations/0035_auto_20170509_0545.py
raster/migrations/0036_auto_20170509_0548.py
django_raster-0.8.1.dist-info/LICENSE
django_raster-0.8.1.dist-info/METADATA
django_raster-0.8.1.dist-info/WHEEL
django_raster-0.8.1.dist-info/top_level.txt
django_raster-0.8.1.dist-info/RECORD
