Metadata-Version: 2.1
Name: django-raster
Version: 0.8.1
Summary: Raster file implementation for Django based on PostGis
Home-page: https://github.com/geodesign/django-raster
Author: Daniel Wiesmann
Author-email: daniel@wiesmann.pt
License: BSD
Keywords: django,raster,gis,gdal,celery,geo,spatial
Platform: UNKNOWN
Classifier: Development Status :: 3 - Alpha
Classifier: Framework :: Django
Classifier: Environment :: Web Environment
Classifier: Intended Audience :: Developers
Classifier: License :: OSI Approved :: BSD License
Classifier: Operating System :: OS Independent
Classifier: Programming Language :: Python
Classifier: Programming Language :: Python :: 3
Classifier: Programming Language :: Python :: 3.4
Classifier: Programming Language :: Python :: 3.5
Classifier: Programming Language :: Python :: 3.6
Classifier: Topic :: Internet :: WWW/HTTP
Classifier: Topic :: Internet :: WWW/HTTP :: Dynamic Content
Classifier: Topic :: Scientific/Engineering :: GIS
Requires-Dist: Django (>=2.0)
Requires-Dist: numpy (>=1.14.2)
Requires-Dist: celery (>=4.1.0)
Requires-Dist: Pillow (>=5.1.0)
Requires-Dist: django-colorful (>=1.2)
Requires-Dist: pyparsing (>=2.2.0)
Requires-Dist: boto3 (>=1.7.9)
